README.md
setup.py
installult/__init__.py
installult/__main__.py
installult.egg-info/PKG-INFO
installult.egg-info/SOURCES.txt
installult.egg-info/dependency_links.txt
installult.egg-info/requires.txt
installult.egg-info/top_level.txt