Metadata-Version: 2.1
Name: installult
Version: 0.6b0
Summary: A Secure and Powerful Python-Telethon Based Library For Ultroid Userbot.
Home-page: https://github.com/TeamUltroid/Ultroid
Author: TeamUltroid
Author-email: teamultroid@protonmail.ch
License: GNU AFFERO GENERAL PUBLIC LICENSE (v3)
Platform: UNKNOWN
Classifier: Programming Language :: Python :: 3
Classifier: Programming Language :: Python :: 3.6
Classifier: Programming Language :: Python :: 3.7
Classifier: Programming Language :: Python :: 3.8
Classifier: Programming Language :: Python :: 3.9
Classifier: License :: OSI Approved :: GNU General Public License v3 (GPLv3)
Classifier: Operating System :: OS Independent
Requires-Python: >=3.6
